<Properties StartupConfiguration="{9E7C3F47-086B-0E0E-8870-9FF672A0C823}|">
  <MonoDevelop.Ide.ItemProperties.Assembly-CSharp PreferredExecutionTarget="Unity.Editor" />
  <MonoDevelop.Ide.Workbench ActiveDocument="Assets/Scripts/NumberWizard.cs">
    <Files>
      <File FileName="Assets/Scripts/SceneLoader.cs" Line="18" Column="2" />
      <File FileName="Assets/Scripts/NumberWizard.cs" Line="31" Column="21" />
    </Files>
  </MonoDevelop.Ide.Workbench>
  <MonoDevelop.Ide.Workspace ActiveConfiguration="Debug" />
  <MonoDevelop.Ide.DebuggingService.Breakpoints>
    <BreakpointStore />
  </MonoDevelop.Ide.DebuggingService.Breakpoints>
  <MonoDevelop.Ide.DebuggingService.PinnedWatches />
  <MultiItemStartupConfigurations />
</Properties>